<?xml version="1.0" encoding="UTF-8"?>
<questestinterop xmlns:wm="http://www.sun.net.tw/WisdomMaster" threshold_score="" score_publish_type="complete">
  <wm:title>a:5:{s:4:"Big5";s:30:"第二十五講　自我評量";s:6:"GB2312";s:9:"undefined";s:2:"en";s:0:"";s:6:"EUC-JP";s:0:"";s:11:"user_define";s:0:"";}</wm:title>
  <item ident="WM_ITEM1_1000100000_10006073_1688992463_392040" title="下列何者非交叉銷售行為的目的？">
    <presentation label="下列何者非交叉銷售行為的目的？">
      <flow>
        <material>
          <mattext>&lt;p&gt;&lt;font color="#000000" size="2"&gt;下列何者非交叉銷售行為的目的？&lt;/font&gt;&lt;/p&gt;</mattext>
        </material>
        <response_lid ident="ANS01" rcardinality="Single" rtiming="No">
          <render_choice shuffle="Yes">
            <response_label ident="1">
              <flow_mat>
                <material>
                  <mattext>鼓勵顧客購買其他產品</mattext>
                </material>
              </flow_mat>
            </response_label>
            <response_label ident="2">
              <flow_mat>
                <material>
                  <mattext>賣出更多的產品</mattext>
                </material>
              </flow_mat>
            </response_label>
            <response_label ident="3">
              <flow_mat>
                <material>
                  <mattext>了解哪些產品可以提高獲利</mattext>
                </material>
              </flow_mat>
            </response_label>
            <response_label ident="4">
              <flow_mat>
                <material>
                  <mattext>刺激現有顧客購買更多高利潤產品</mattext>
                </material>
              </flow_mat>
            </response_label>
          </render_choice>
        </response_lid>
      </flow>
    </presentation>
    <resprocessing>
      <outcomes>
        <decvar vartype="Integer" defaultval="0"/>
      </outcomes>
      <respcondition title="Correct">
        <conditionvar>
          <varequal respident="ANS01">2</varequal>
        </conditionvar>
        <setvar action="Set">1</setvar>
        <displayfeedback feedbacktype="Response" linkrefid="Correct"/>
      </respcondition>
    </resprocessing>
    <itemfeedback ident="Correct">
      <flow_mat>
        <material>
          <mattext/>
        </material>
      </flow_mat>
      <solution>
        <solutionmaterial>
          <material>
            <mattext/>
          </material>
        </solutionmaterial>
        <wm:refurl>http://</wm:refurl>
      </solution>
      <hint enable="false">
        <hintmaterial>
          <material>
            <mattext/>
          </material>
        </hintmaterial>
      </hint>
    </itemfeedback>
    <wm:hardlevel>3</wm:hardlevel>
    <wm:class>
      <wm:version>0</wm:version>
      <wm:volume>0</wm:volume>
      <wm:chapter>25</wm:chapter>
      <wm:paragraph>1</wm:paragraph>
      <wm:section>0</wm:section>
    </wm:class>
  </item>
  <item ident="WM_ITEM1_1000100000_10006073_1688992523_529638" title="購物籃分析是指：">
    <presentation label="購物籃分析是指：">
      <flow>
        <material>
          <mattext>&lt;p&gt;&lt;font color="#000000" size="2"&gt;購物籃分析是指：&lt;/font&gt;&lt;/p&gt;</mattext>
        </material>
        <response_lid ident="ANS01" rcardinality="Single" rtiming="No">
          <render_choice shuffle="Yes">
            <response_label ident="1">
              <flow_mat>
                <material>
                  <mattext>產品關連分析</mattext>
                </material>
              </flow_mat>
            </response_label>
            <response_label ident="2">
              <flow_mat>
                <material>
                  <mattext>採購分析</mattext>
                </material>
              </flow_mat>
            </response_label>
            <response_label ident="3">
              <flow_mat>
                <material>
                  <mattext>採購傾向分析</mattext>
                </material>
              </flow_mat>
            </response_label>
            <response_label ident="4">
              <flow_mat>
                <material>
                  <mattext>價格彈性模式</mattext>
                </material>
              </flow_mat>
            </response_label>
          </render_choice>
        </response_lid>
      </flow>
    </presentation>
    <resprocessing>
      <outcomes>
        <decvar vartype="Integer" defaultval="0"/>
      </outcomes>
      <respcondition title="Correct">
        <conditionvar>
          <varequal respident="ANS01">1</varequal>
        </conditionvar>
        <setvar action="Set">1</setvar>
        <displayfeedback feedbacktype="Response" linkrefid="Correct"/>
      </respcondition>
    </resprocessing>
    <itemfeedback ident="Correct">
      <flow_mat>
        <material>
          <mattext/>
        </material>
      </flow_mat>
      <solution>
        <solutionmaterial>
          <material>
            <mattext/>
          </material>
        </solutionmaterial>
        <wm:refurl>http://</wm:refurl>
      </solution>
      <hint enable="false">
        <hintmaterial>
          <material>
            <mattext/>
          </material>
        </hintmaterial>
      </hint>
    </itemfeedback>
    <wm:hardlevel>3</wm:hardlevel>
    <wm:class>
      <wm:version>0</wm:version>
      <wm:volume>0</wm:volume>
      <wm:chapter>25</wm:chapter>
      <wm:paragraph>2</wm:paragraph>
      <wm:section>0</wm:section>
    </wm:class>
  </item>
  <item ident="WM_ITEM1_1000100000_10006073_1688992581_593734" title="欲瞭解不同族群顧客最可能購買的產品應 ...">
    <presentation label="欲瞭解不同族群顧客最可能購買的產品應 ...">
      <flow>
        <material>
          <mattext>&lt;p&gt;&lt;font color="#000000" size="2"&gt;欲瞭解不同族群顧客最可能購買的產品應該使用：&lt;/font&gt;&lt;/p&gt;</mattext>
        </material>
        <response_lid ident="ANS01" rcardinality="Single" rtiming="No">
          <render_choice shuffle="Yes">
            <response_label ident="1">
              <flow_mat>
                <material>
                  <mattext>採購動向分析</mattext>
                </material>
              </flow_mat>
            </response_label>
            <response_label ident="2">
              <flow_mat>
                <material>
                  <mattext>產品關連分析</mattext>
                </material>
              </flow_mat>
            </response_label>
            <response_label ident="3">
              <flow_mat>
                <material>
                  <mattext>採購傾向分析</mattext>
                </material>
              </flow_mat>
            </response_label>
            <response_label ident="4">
              <flow_mat>
                <material>
                  <mattext>價格彈性分析</mattext>
                </material>
              </flow_mat>
            </response_label>
          </render_choice>
        </response_lid>
      </flow>
    </presentation>
    <resprocessing>
      <outcomes>
        <decvar vartype="Integer" defaultval="0"/>
      </outcomes>
      <respcondition title="Correct">
        <conditionvar>
          <varequal respident="ANS01">3</varequal>
        </conditionvar>
        <setvar action="Set">1</setvar>
        <displayfeedback feedbacktype="Response" linkrefid="Correct"/>
      </respcondition>
    </resprocessing>
    <itemfeedback ident="Correct">
      <flow_mat>
        <material>
          <mattext/>
        </material>
      </flow_mat>
      <solution>
        <solutionmaterial>
          <material>
            <mattext/>
          </material>
        </solutionmaterial>
        <wm:refurl>http://</wm:refurl>
      </solution>
      <hint enable="false">
        <hintmaterial>
          <material>
            <mattext/>
          </material>
        </hintmaterial>
      </hint>
    </itemfeedback>
    <wm:hardlevel>3</wm:hardlevel>
    <wm:class>
      <wm:version>0</wm:version>
      <wm:volume>0</wm:volume>
      <wm:chapter>25</wm:chapter>
      <wm:paragraph>3</wm:paragraph>
      <wm:section>0</wm:section>
    </wm:class>
  </item>
  <item ident="WM_ITEM1_1000100000_10006073_1688992655_503995" title="企業預測顧客可能行為可了解哪些問題？">
    <presentation label="企業預測顧客可能行為可了解哪些問題？">
      <flow>
        <material>
          <mattext>&lt;p&gt;&lt;font color="#000000" size="2"&gt;企業預測顧客可能行為可了解哪些問題？&lt;/font&gt;&lt;/p&gt;</mattext>
        </material>
        <response_str ident="FIB91" rcardinality="Ordered" rtiming="No">
          <render_fib fibtype="String" prompt="Box" rows="10" columns="50">
            <response_label ident="A"/>
          </render_fib>
        </response_str>
      </flow>
    </presentation>
    <resprocessing>
      <outcomes>
        <decvar vartype="Integer" defaultval="0"/>
      </outcomes>
    </resprocessing>
    <itemfeedback ident="AllCorrect">
      <flow_mat>
        <material>
          <mattext>All correct. Well done.</mattext>
        </material>
      </flow_mat>
      <solution>
        <solutionmaterial>
          <material>
            <mattext>&lt;p&gt;答:&lt;/p&gt;

&lt;p&gt;(1)先買先打折或價格調整可能造成那個部分的現有顧客流失風險&lt;br /&gt;
(2)簡化目標行銷活動，集中行銷目標在更小的顧客群或特殊產品上&lt;br /&gt;
(3)將某些產品配套以固定價格銷售，鼓勵更多產品購買或提高利潤&lt;br /&gt;
(4)找出可能和其他產品進行交叉銷售的產品&lt;br /&gt;
(5)可以瞭解顧客的獲利性，以避免浪費太多的服務成本於不可能提供獲利的顧客上&lt;/p&gt;</mattext>
          </material>
        </solutionmaterial>
        <wm:refurl>http://</wm:refurl>
      </solution>
      <hint enable="false">
        <hintmaterial>
          <material>
            <mattext/>
          </material>
        </hintmaterial>
      </hint>
    </itemfeedback>
    <wm:hardlevel>3</wm:hardlevel>
    <wm:class>
      <wm:version>0</wm:version>
      <wm:volume>0</wm:volume>
      <wm:chapter>25</wm:chapter>
      <wm:paragraph>4</wm:paragraph>
      <wm:section>0</wm:section>
    </wm:class>
  </item>
</questestinterop>
